pycollab/__init__.py
pycollab/p1.py
pycollab/p2.py
pycollab/p5p6.py
pycollab/p7.py
pycollab/p8.py
pycollab/p9.py
pycollab-0.3.1.dist-info/LICENCE.txt
pycollab-0.3.1.dist-info/METADATA
pycollab-0.3.1.dist-info/WHEEL
pycollab-0.3.1.dist-info/top_level.txt
pycollab-0.3.1.dist-info/RECORD
