Metadata-Version: 2.1
Name: pycollab
Version: 0.3.1
Summary: Py collab
Home-page: UNKNOWN
Author: usnohooks
Author-email: pycollab@proton.me
License: UNKNOWN
Platform: UNKNOWN
Classifier: Programming Language :: Python :: 3
Classifier: License :: OSI Approved :: MIT License
Classifier: Operating System :: OS Independent
